{
    "items": [
        {
            "recommend": -5,
            "title": "프리미엄 듀록 꽃삼겹살 1kg (500g+500g) 외",
            "comment": 29,
            "shoppingmall": "위메프",
            "price": "12,900원",
            "deliveryfee": "무료",
            "category": "먹거리",
            "time": "09:45",
            "author": "낙화유소"
        },
        {
            "recommend": 45,
            "title": "헤드앤숄더 클리니컬 스트렝스 2EA",
            "comment": 153,
            "shoppingmall": "11번가",
            "price": "22,000원",
            "deliveryfee": "무료",
            "category": "생활용품",
            "time": "09:28",
            "author": "82년생이주영"
        },
        {
            "recommend": 10,
            "title": "베트남 아카시아 골드망고(A등급) 4kg",
            "comment": 17,
            "shoppingmall": "위메프",
            "price": "21,900원",
            "deliveryfee": "무료",
            "category": "먹거리",
            "time": "09:03",
            "author": "낙화유소"
        },
        {
            "recommend": -13,
            "title": "ACER NITRO XV272U W2",
            "comment": 24,
            "shoppingmall": "알리",
            "price": "330,185원",
            "deliveryfee": "무료",
            "category": "PC제품",
            "time": "06:04",
            "author": "FPS가이지"
        },
        {
            "recommend": 20,
            "title": "펩시제로슈거 라임향 210ml 60캔",
            "comment": 21,
            "shoppingmall": "네이버",
            "price": "22,520원",
            "deliveryfee": "무료",
            "category": "먹거리",
            "time": "02:54",
            "author": "삼십이암페어"
        },
        {
            "recommend": 58,
            "title": "toocki GaN 67w 고속충전기",
            "comment": 170,
            "shoppingmall": "알리 천원상점",
            "price": "9,000원",
            "deliveryfee": "무료",
            "category": "가전제품",
            "time": "02:50",
            "author": "디도스나이트"
        },
        {
            "recommend": 16,
            "title": "닛신 UFO , 잇페이짱 오리지날 12개",
            "comment": 53,
            "shoppingmall": "위메프플러스",
            "price": "체감가18,220",
            "deliveryfee": "무료",
            "category": "먹거리",
            "time": "01:45",
            "author": "아오배고픈데"
        },
        {
            "recommend": 17,
            "title": "하늘보리500ml * 20개 외 누룽지/결명자/헛개차/자색옥수수",
            "comment": 9,
            "shoppingmall": "티몬",
            "price": "9,000원",
            "deliveryfee": "무료",
            "category": "먹거리",
            "time": "01:02",
            "author": "목성"
        },
        {
            "recommend": 8,
            "title": "닛신 컵누들 라멘 3종 오리지날,씨푸드,카레 12개",
            "comment": 37,
            "shoppingmall": "위메프플러스",
            "price": "16,680원",
            "deliveryfee": "무료",
            "category": "먹거리",
            "time": "01:00",
            "author": "아오배고픈데"
        },
        {
            "recommend": 12,
            "title": "고메 소바바치킨 양념순살375g 2봉 허니순살1봉 [토스페이계좌/카카오페이]",
            "comment": 22,
            "shoppingmall": "티몬",
            "price": "13,788원",
            "deliveryfee": "무료",
            "category": "먹거리",
            "time": "00:56",
            "author": "목성"
        },
        {
            "recommend": 17,
            "title": "햇반 컵반 8개세트 토스페이",
            "comment": 22,
            "shoppingmall": "티몬",
            "price": "11,232원",
            "deliveryfee": "무료",
            "category": "먹거리",
            "time": "00:46",
            "author": "식후유산소"
        },
        {
            "recommend": 20,
            "title": "얼티브 비건프로틴 250ml x 18개",
            "comment": 20,
            "shoppingmall": "티몬",
            "price": "15,840원",
            "deliveryfee": "무료",
            "category": "먹거리",
            "time": "00:42",
            "author": "잘익은홍시"
        },
        {
            "recommend": 15,
            "title": "닛신 라오 (라왕) 라멘 6+6",
            "comment": 60,
            "shoppingmall": "위메프플러스",
            "price": "체감가23,830",
            "deliveryfee": "무료",
            "category": "먹거리",
            "time": "00:40",
            "author": "아오배고픈데"
        },
        {
            "recommend": 44,
            "title": "스팸 클래식 200g x 10개",
            "comment": 43,
            "shoppingmall": "네이버",
            "price": "19,900원",
            "deliveryfee": "무료",
            "category": "먹거리",
            "time": "00:39",
            "author": "산탄"
        },
        {
            "recommend": 1,
            "title": "리큐 미니파워 멀티클린 캡슐세제 60개입 + 드라이시트 10매",
            "comment": 1,
            "shoppingmall": "롯데온",
            "price": "15,210원",
            "deliveryfee": "무료",
            "category": "생활용품",
            "time": "00:35",
            "author": "삼십이암페어"
        },
        {
            "recommend": 16,
            "title": "제일제당 동치미물냉면 2인분+함흥비빔냉면 2인분 x 4개(총16인분)",
            "comment": 12,
            "shoppingmall": "티몬",
            "price": "21,141원",
            "deliveryfee": "무료",
            "category": "먹거리",
            "time": "00:29",
            "author": "본인:"
        },
        {
            "recommend": 5,
            "title": "노 레스트 포 더 위키드",
            "comment": 8,
            "shoppingmall": "그린맨게이밍",
            "price": "29,300원",
            "deliveryfee": "무료",
            "category": "SW/게임",
            "time": "00:28",
            "author": "수면아래생명의첫"
        },
        {
            "recommend": 10,
            "title": "3초떡볶이 2팩+2팩",
            "comment": 31,
            "shoppingmall": "11번",
            "price": "6,460원",
            "deliveryfee": "무료",
            "category": "먹거리",
            "time": "00:22",
            "author": "이금파"
        },
        {
            "recommend": 15,
            "title": "더단백 프로틴 드링크 250ml 18+18팩",
            "comment": 76,
            "shoppingmall": "위메프",
            "price": "40,860원",
            "deliveryfee": "무료",
            "category": "먹거리",
            "time": "00:18",
            "author": "특빠원"
        },
        {
            "recommend": 6,
            "title": "하루견과 넛츠오리진스 20G X 100봉",
            "comment": 10,
            "shoppingmall": "롯데온",
            "price": "38,920원",
            "deliveryfee": "무료",
            "category": "먹거리",
            "time": "00:17",
            "author": "산탄"
        }
    ]
}