{
    "items": [
        {
            "id": 1,
            "recommend": -5,
            "title": "프리미엄 듀록 꽃삼겹살 1kg (500g+500g) 외",
            "comment": 29,
            "shoppingmall": "위메프",
            "price": "12,900원",
            "deliveryfee": "무료",
            "category": "먹거리",
            "time": "09:45",
            "author": "낙화유소",
            "description": "프리미엄 돼지고기"
        },
        {
            "id": 2,
            "recommend": 45,
            "title": "헤드앤숄더 클리니컬 스트렝스 2EA",
            "comment": 153,
            "shoppingmall": "11번가",
            "price": "22,000원",
            "deliveryfee": "무료",
            "category": "생활용품",
            "time": "09:28",
            "author": "82년생이주영",
            "description": "헤드앤숄더 샴푸"
        },
        {
            "id": 3,
            "recommend": 10,
            "title": "베트남 아카시아 골드망고(A등급) 4kg",
            "comment": 17,
            "shoppingmall": "위메프",
            "price": "21,900원",
            "deliveryfee": "무료",
            "category": "먹거리",
            "time": "09:03",
            "author": "낙화유소",
            "description": "베트남 아카시아 망고"
        },
        {
            "id": 4,
            "recommend": -13,
            "title": "ACER NITRO XV272U W2",
            "comment": 24,
            "shoppingmall": "알리",
            "price": "330,185원",
            "deliveryfee": "무료",
            "category": "PC제품",
            "time": "06:04",
            "author": "FPS가이지",
            "description": "게이밍 모니터"
        },
        {
            "id": 5,
            "recommend": 20,
            "title": "펩시제로슈거 라임향 210ml 60캔",
            "comment": 21,
            "shoppingmall": "네이버",
            "price": "22,520원",
            "deliveryfee": "무료",
            "category": "먹거리",
            "time": "02:54",
            "author": "삼십이암페어",
            "description": "제로슈거 음료"
        },
        {
            "id": 6,
            "recommend": 58,
            "title": "toocki GaN 67w 고속충전기",
            "comment": 170,
            "shoppingmall": "알리 천원상점",
            "price": "9,000원",
            "deliveryfee": "무료",
            "category": "가전제품",
            "time": "02:50",
            "author": "디도스나이트",
            "description": "고속 충전기"
        },
        {
            "id": 7,
            "recommend": 16,
            "title": "닛신 UFO , 잇페이짱 오리지날 12개",
            "comment": 53,
            "shoppingmall": "위메프플러스",
            "price": "체감가18,220",
            "deliveryfee": "무료",
            "category": "먹거리",
            "time": "01:45",
            "author": "아오배고픈데",
            "description": "일본 컵라면"
        },
        {
            "id": 8,
            "recommend": 17,
            "title": "하늘보리500ml * 20개 외 누룽지/결명자/헛개차/자색옥수수",
            "comment": 9,
            "shoppingmall": "티몬",
            "price": "9,000원",
            "deliveryfee": "무료",
            "category": "먹거리",
            "time": "01:02",
            "author": "목성",
            "description": "보리차"
        },
        {
            "id": 9,
            "recommend": 8,
            "title": "닛신 컵누들 라멘 3종 오리지날,씨푸드,카레 12개",
            "comment": 37,
            "shoppingmall": "위메프플러스",
            "price": "16,680원",
            "deliveryfee": "무료",
            "category": "먹거리",
            "time": "01:00",
            "author": "아오배고픈데",
            "description": "일본 컵라면"
        },
        {
            "id": 10,
            "recommend": 12,
            "title": "고메 소바바치킨 양념순살375g 2봉 허니순살1봉 [토스페이계좌/카카오페이]",
            "comment": 22,
            "shoppingmall": "티몬",
            "price": "13,788원",
            "deliveryfee": "무료",
            "category": "먹거리",
            "time": "00:56",
            "author": "목성",
            "description": "양념 순살 치킨"
        },
        {
            "id": 11,
            "title": "[G Market] 2XCGN Silymarin Complex 1년치 300mg 360 베지캡슐 (삼카) (49,060원) (무료)",
            "date": "2024.06.11 13:11",
            "author": "Coco Johnny",
            "views": "9102",
            "likes": "14",
            "comment_count": "21",
            "related_url": "https://item.gmarket.co.kr/Item?goodscode=2904552108",
            "shoppingmall": "G Market",
            "product_name": "2XCGN Silymarin Complex 1년치 300mg 360 베지캡슐 (삼카)",
            "price": "49,060원",
            "deliveryfee": "무료",
            "article": [
                "유클레 쿠폰 + 20% 쿠폰 + 삼카 할인 사용 시 49,060원, 병당 24,530원(삼카 사용 안 할 경우 25,030원)",
                "지난번보다 싸서 올립니다",
                "요즘은 종비랑 오메가랑 같이 먹어야 거의 필수 보충제 같네요",
                "간세포 보호 및 재생에 도움이 되니 자기 전에 복용하는 것이 좋다고 합니다"
            ],
            "comments": "댓글"
        },
        {
            "id": 12,
            "title": "[인터파크] 닌텐도 스위치 페이퍼 마리오 1000년의 문 (2024) (농카 51,700) (무료배송)",
            "date": "2024.06.11 14:07",
            "author": "Uni-chan",
            "views": "23612",
            "likes": "6",
            "comment_count": "21",
            "related_url": "http://m.shop.interpark.com/product/15444317697/0000100000",
            "shoppingmall": "인터파크",
            "product_name": "닌텐도 스위치 페이퍼 마리오 1000년의 문 (2024)",
            "price": "농카 51,700",
            "deliveryfee": "무료배송",
            "article": [
                "5월 23일 출시된 페이퍼 마리오",
                "1000년의 문 리메이크 버전",
                "농카 결제 시 51,700원",
                "삼카/록카 결제 시 52,250원"
            ],
            "comments": "댓글"
        },
        {
            "id": 13,
            "title": "[쿠팡] 킬라 액상 리필 6개 (18,290원) (쿠팡와우 무료)",
            "date": "2024.06.11 13:59",
            "author": "아 배고파",
            "views": "11619",
            "likes": "11",
            "comment_count": "42",
            "related_url": "https://link.coupang.com/a/bFauxt",
            "shoppingmall": "쿠팡",
            "product_name": "킬라 액상 리필 6개",
            "price": "18,290원",
            "deliveryfee": "쿠팡와우 무료",
            "article": [
                "액상 쓰니까 확실히 잠 잘옴, 개좋음",
                "+ 다이소에서 개당 3천원에 파네요",
                "약국이나 쿠팡에서는 개당 5천~6천원",
                "다이소 미쳤네, 왜 이렇게 싸움??"
            ],
            "comments": "댓글"
        },
        {
            "id": 14,
            "title": "[G Market] 남녀공용 아이스 쿨 9부 밴딩바지 1+1 (13,130원) (무료)",
            "date": "2024.06.11 13:58",
            "author": "잡코리아",
            "views": "26434",
            "likes": "4",
            "comment_count": "34",
            "related_url": "https://item.gmarket.co.kr/Item?goodscode=3696699287",
            "shoppingmall": "G Market",
            "product_name": "남녀공용 아이스 쿨 9부 밴딩바지 1+1",
            "price": "13,130원",
            "deliveryfee": "무료",
            "article": [],
            "comments": "댓글"
        },
        {
            "id": 15,
            "title": "[위메프] 오뚜기밥 백미 210g x 24 (16,990원) (무료)",
            "date": "2024.06.11 13:46",
            "author": "카나푸키",
            "views": "9540",
            "likes": "19",
            "comment_count": "20",
            "related_url": "https://plus.wemakeprice.com/gmkt.inc/Mobile/Goods/Goods.aspx?goodscode=1186660147&jaehuid=",
            "shoppingmall": "위메프",
            "product_name": "오뚜기밥 백미 210g x 24",
            "price": "16,990원",
            "deliveryfee": "무료",
            "article": [],
            "comments": "댓글"
        }
    ]
}